common_list_grade_marks/__init__.py
common_list_grade_marks-0.1.dist-info/LICENCE.txt
common_list_grade_marks-0.1.dist-info/METADATA
common_list_grade_marks-0.1.dist-info/WHEEL
common_list_grade_marks-0.1.dist-info/top_level.txt
common_list_grade_marks-0.1.dist-info/RECORD
